Metadata-Version: 1.0
Name: face-recognition-util
Version: 0.0.6
Summary: time and path tool
Home-page: https://github.com/reventhao/face_recognition_util
Author: reventhao
Author-email: ren895873@gmail.com
License: MIT Licence
Keywords: face_recognition_util
Platform: any
